{"url":"https://www.rocketpunch.com//jobs/65834/%EC%82%B0%ED%83%80%ED%86%A0%EC%9D%B5-Frontend-Developer-%EC%82%B0%EC%97%85%EA%B8%B0%EB%8A%A5%EC%9A%94%EC%9B%90%EC%A0%84%EB%AC%B8%EC%97%B0%EA%B5%AC%EC%9A%94%EC%9B%90-%EB%B3%B5%EB%AC%B4-%EA%B0%80%EB%8A%A5","title":"[산타토익] Frontend Developer (산업기능요원/전문연구요원 복무 가능)","origin":"뤼이드!","start_date":"11/14 ","newbie":"소경력","content":["\n        주요 업무\n                    • 머신 러닝에 기반한 교육 서비스의 가장 앞부분을 구현합니다.• JavaScript의 장점을 적극 활용해, 인프라 관련 코드도 직접 작성하고 관리합니다.• 사내 RFC를 제안하고 관리합니다. 뤼이드 개발팀만의 개발 규약을 만들어 예측가능한 코드를 작성합니다.• 테스트 코드를 작성합니다. 잦은 기능변화에도 앱의 동작을 쉽게 확인하고 확장합니다.• 자…\n            더 보기\n            • 머신 러닝에 기반한 교육 서비스의 가장 앞부분을 구현합니다.• JavaScript의 장점을 적극 활용해, 인프라 관련 코드도 직접 작성하고 관리합니다.• 사내 RFC를 제안하고 관리합니다. 뤼이드 개발팀만의 개발 규약을 만들어 예측가능한 코드를 작성합니다.• 테스트 코드를 작성합니다. 잦은 기능변화에도 앱의 동작을 쉽게 확인하고 확장합니다.• 자동화를 중요시합니다. 업무흐름, 정적분석, 테스트, 배포를 완전히 자동화하기 위해 노력합니다.\n\n      ","\n        업무 관련 기술 / 활동 분야\n        \n          Front-end\n          JavaScript\n          Node.js\n        \n      ","\n        채용 상세\n                    자격요건 • 머신 러닝에 기반한 교육 서비스의 가장 앞부분을 구현합니다. • JavaScript의 장점을 적극 활용해, 인프라 관련 코드도 직접 작성하고 관리합니다. • 사내 RFC를 제안하고 관리합니다. 뤼이드 개발팀만의 개발 규약을 만들어 예측가능한 코드를 작성합니다. • 테스트 코드를 작성합니다. 잦은 기능변화에도 앱의 동작을 쉽게 확인하고 확…\n            더 보기\n            자격요건 • 머신 러닝에 기반한 교육 서비스의 가장 앞부분을 구현합니다. • JavaScript의 장점을 적극 활용해, 인프라 관련 코드도 직접 작성하고 관리합니다. • 사내 RFC를 제안하고 관리합니다. 뤼이드 개발팀만의 개발 규약을 만들어 예측가능한 코드를 작성합니다. • 테스트 코드를 작성합니다. 잦은 기능변화에도 앱의 동작을 쉽게 확인하고 확장합니다. • 자동화를 중요시합니다. 업무흐름, 정적분석, 테스트, 배포를 완전히 자동화하기 위해 노력합니다.우대사항지원자분의 기술 스택을 적극 존중합니다. • 다수의 팀 프로젝트를 수행해 본 경험이 있으신 분• 뤼이드의 도전에 동참하고 끝없이 성장하기를 원하시는 분• 항상 [왜?]라는 질문에서부터 출발하여 스스로 동기부여를 받으시는 분• 자유로운 환경에서 최대한 퍼포먼스를 낼 수 있으신 분\n"]}