{"url":"https://www.rocketpunch.com//jobs/65362/Essay-writer","title":"Essay writer","origin":"제이앤비에세이컨설팅","start_date":"11/08 ","newbie":"신입경력","content":["\n        주요 업무\n        WE, J\u0026B Essay Consulting, are now looking for highly qualified essay writers/ consultants. This job is ideal for someone looking for flexible, intellectually stimulating work. Pay is commensurate with experience and length of work with J\u0026B Essay Consulting.\n      ","\n        업무 관련 기술 / 활동 분야\n        \n          WordPress\n        \n      ","\n        채용 상세\n        자격 조건 (Qualifications)•\t영어권 국가 4년제 대학교 재학생 및 졸업생•\t영어 에세이 작문 및 컨설팅 실력을 갖추신 분•\t프리랜서로서 시간을 융통성 있게 사용하실 수 있는 분•\t꼼꼼하고 책임감 있는 성격을 갖추신 분, 낙관적인 마인드를 지니신 분•\t에세이 컨설팅 업무 경험 있으신 분 (우대)•\tMinimum of bachelor’s degree in an English-speaking country required (Applications from current undergraduates will be also reviewed)•\tExperience with essay consulting (brainstorming, outlining, writing) preferred•\tAdvanced English writing skills•\tAble to work flexible hours and follow given deadlines•\tDetail-oriented, highly responsible and positive주요 업무 (Responsibilities)•\t아카데믹 영어 에세이/어드미션 에세이 컨텐츠를 활용하여 완성도 있게 작성•\t가이드라인에 맞춰 에세이를 작성하여 마감 시간에 맞춰 제공•\tWrite/provide feedback for English essays on various academic topics/ admission essay prompts•\tProvide clients thorough writing guidance based on the prepared curriculum•\tEnsure to meet clients’ requests and expectations"]}