{"url":"https://www.rocketpunch.com//jobs/56047/React-%EC%9B%B9%EB%AA%A8%EB%B0%94%EC%9D%BC-%EA%B0%9C%EB%B0%9C%EC%9E%90","title":"React 웹/모바일 개발자","origin":"리디(주) - 라프텔 사업본부","start_date":"02/18 ","newbie":"경력","content":["\n        주요 업무\n                    “합법적으로 무료로 애니메이션을 감상할 수 있는 서비스”라프텔의 팀원이 되실 개발자님을 모십니다.현재 어둠의 경로를 통해 무료로 애니를 감상하는 사용자들이,미래에 돈을 지불하더라도 사용하고 싶은 매력적인 서비스를함께 만들어 갈 새로운 팀원을 충원하고 있습니다.라프텔 프론트엔드 개발자는 PC, 모바일, TV 환경에서 애니메이션 스트리밍 서비스를 개발하…\n            더 보기\n            “합법적으로 무료로 애니메이션을 감상할 수 있는 서비스”라프텔의 팀원이 되실 개발자님을 모십니다.현재 어둠의 경로를 통해 무료로 애니를 감상하는 사용자들이,미래에 돈을 지불하더라도 사용하고 싶은 매력적인 서비스를함께 만들어 갈 새로운 팀원을 충원하고 있습니다.라프텔 프론트엔드 개발자는 PC, 모바일, TV 환경에서 애니메이션 스트리밍 서비스를 개발하며, 사용자들에게 즐겁고 편안한 경험을 제공하기 위하여 끊임없이 노력합니다.또한 더 좋은 서비스를 개발하기 위하여 다른 직군의 팀원들과의 소통을 거쳐 함께 서비스를 지속적으로 개선해 나갑니다.다양한 플랫폼을 넘나드는 한국의 대표적인 애니 스트리밍 서비스를 만들어 나가며 함께 성장하고자 하는 프론트엔드 개발자 분들의 많은 관심과 지원 바랍니다!\n\n      ","\n        업무 관련 기술 / 활동 분야\n        \n          TypeScript\n          JavaScript\n          Redux\n          React\n          react-native\n          Jest\n        \n      ","\n        채용 상세\n                    담당업무- React를 사용하여 애니메이션 스트리밍 플랫폼을 만듭니다. 자격요건- 프론트엔드 개발 경력 2년 이상- React 또는 React Native를 사용한 프로덕트 개발 및 릴리즈 경험- React 개발 흐름과 JavaScript에 대한 깊은 이해우대사항- 프론트엔드 유닛/통합 테스트 경험- TypeScript 사용 경험- Kotlin 또는…\n            더 보기\n            담당업무- React를 사용하여 애니메이션 스트리밍 플랫폼을 만듭니다. 자격요건- 프론트엔드 개발 경력 2년 이상- React 또는 React Native를 사용한 프로덕트 개발 및 릴리즈 경험- React 개발 흐름과 JavaScript에 대한 깊은 이해우대사항- 프론트엔드 유닛/통합 테스트 경험- TypeScript 사용 경험- Kotlin 또는 Swift 코드에 익숙 하신 분- 새로운 기술에 관심이 많으신 분- 주어진 시안을 디자이너의 의도대로 100% 반영해 낼 수 있는 분- 스마트 TV 앱 개발 경험\n\n            \n              \n                  \n                  \n                \n            \n          "]}