{"url":"https://programmers.co.kr/job_positions/941","title":"모바일 개발자","origin":"빅트리","start_date":"","newbie":false,"content":["기술 스택\nObjective-C Swift iOS","업무 소개\n\n빅트리는 자체개발한 첨단 인공지능 빅데이터 분석 엔진으로 금융 데이터 분석과 텍스트 분석 솔루션을 공급하는 금융 로보어드바이저 분야 핀테크 벤처기업 입니다.\n\n기술위주의 벤처기업으로 2015년부터 지금까지 오롯이 연구에 매진해 연구 성과로 수익을 창출하는 핀테크 기업으로 빅봇을 전세계 대표적인 인공지능 금융 플랫폼으로 만들고 빅봇을 통해 누구나 쉽게 금융생활을 할 수 있는 세상을 만드는 것을 목표로 하고 있습니다.\n\n“개인도 전문 펀드매니저처럼 투자할 수 있다.”\n\n우리는 개인투자자가 전문 펀드매니저처럼 투자할 수 있도록 금융정보 분석과 체계적인 방법론을 제공해드리고자 설립한 회사입니다. 우리는 정보를 공개함으로써 더 큰 회사로 성장할 수 있다는 비전을 가지고 있기 때문입니다.\n\n빅데이터 분석을 통해서 만들어진 투자정보를 개인에게 효과적으로 전달하기 위한 모바일, 데스크탑 UI/UX를 실험하고 사용자의 요구를 수용할 수 있는 코드를 작성합니다. 어제와 다른 경험을 만들기 위해서 새로운 기술과 구현방법을 끊임없이 탐색 및 연구하고, 리드하며 개발자 커뮤니티에 적극적으로 참여해야 합니다.","자격 조건\n5년 이상의 iOS, Android 앱 개발 경력\nGoogle의 Material Design에 대한 높은 수준의 이해\nApple의 Human Interface Guideline에 대한 높은 수준의 이해\nJava, Kotlin 프로그래밍 기술\nObjective-C, Swift 프로그래밍 기술\nFlutter를 써보았다면 큰 장점\nMVC style이나 MVVM 등의 프레임워크를 잘 이해하고 활용하실 수 있어야 합니다.\n문제 해결, 디버깅, 장애 해결 등에 있어서 팀으로 문제를 해결 할 수 있는 분\n본인이 하고 있는 일과 하려는 일에 대해서 잘 설명하고 문서로 작성하고 발표할 수 있는 능력","우대 사항"]}