{"url":"https://www.rocketpunch.com//jobs/66068/Senior-UXUI-Designer","title":"Senior UX/UI Designer","origin":"핀다","start_date":"02/07 ","newbie":"경력","content":["\n        주요 업무\n                    - 핀다의 안드로이드, iOS 앱의 대출신청 및 대출분석과 관련한 메인 사용 경험을 설계하기 위한 UXUI 디자인 리드- 개인화된 사용자 경험을 전달하기 위한 핀다 서비스 UXUI 개선\n\n      ","\n        업무 관련 기술 / 활동 분야\n        \n          Sketch\n          zeplin\n          InVision\n          UX디자인\n          UI디자인\n          모바일디자인\n        \n      ","\n        채용 상세\n                    자격요건-B2C 모바일 앱 UXUI 디자이너 또는 디자인 리드 역할로 최소 3년 이상 경험이 있는 분-앱 서비스나 기능 디자인 개선을 Build \u003e Experiment \u003e Learn Loop 과정을 통해 진행해 보신 분-데이터 분석, 사용자 인터뷰, A/B 테스트 등 다양한 방법론을 통해 사용자 경험을 개선해 본 경험이 있는 분-자신의 생…\n            더 보기\n            자격요건-B2C 모바일 앱 UXUI 디자이너 또는 디자인 리드 역할로 최소 3년 이상 경험이 있는 분-앱 서비스나 기능 디자인 개선을 Build \u003e Experiment \u003e Learn Loop 과정을 통해 진행해 보신 분-데이터 분석, 사용자 인터뷰, A/B 테스트 등 다양한 방법론을 통해 사용자 경험을 개선해 본 경험이 있는 분-자신의 생각을 프로토타입이나 기획서로 정리하여 비즈니스, 개발, 기획 같은 다양한 포지션의 팀들과 협업 커뮤니케이션을 잘 이끄시는 분우대사항-10만 이상의 B2C 앱서비스를 직접 디자인하며 성공/실패 경험이 뚜렷하게 있으신 분-핀테크 서비스에 높은 관심 및 니즈가 있으신 분 -데이터 분석, 프로토타입 툴의 사용 경험이 풍부하신 분-신규 서비스까지 통합하는 디자인에 대한 큰그림을 고민하실 수 있는 분\n"]}