{"url":"https://www.rocketpunch.com//jobs/51960/%EC%82%AC%EC%9A%A9%EC%9E%90-%EA%B2%BD%ED%97%98%EC%97%90-%EC%98%88%EB%AF%BC%ED%95%98%EC%8B%A0-%ED%94%84%EB%A1%A0%ED%8A%B8%EC%97%94%EB%93%9C-%EA%B0%9C%EB%B0%9C%EC%9E%90%EB%A5%BC-%EB%AA%A8%EC%8B%9C%EA%B3%A0-%EC%9E%88%EC%96%B4%EC%9A%94%EC%9D%B8%ED%84%B4-%EA%B0%80%EB%8A%A5","title":"사용자 경험에 예민하신 프론트엔드 개발자를 모시고 있어요.[인턴 가능]","origin":"크프","start_date":"02/11 ","newbie":"인턴경력","content":["\n        주요 업무\n                    \u003c 크프는 이런 회사 \u003e- 빠르게 성장하는 스타트업임. - 최근에 투자유치를 마무리하고 2020년에 신나게 달려볼 준비를 하고 있음.- 투자사에 대한 정보는 로켓펀치 회사 정보에도 나와있음.(아주 아주 좋은 곳에서 투자를 받았다고 자부함_자본주의만세) - 모두 영어로 호칭함. 직급 없음. 라떼는 말이야 식의 꼰대짓 없음. - 토익 토플 점…\n            더 보기\n            \u003c 크프는 이런 회사 \u003e- 빠르게 성장하는 스타트업임. - 최근에 투자유치를 마무리하고 2020년에 신나게 달려볼 준비를 하고 있음.- 투자사에 대한 정보는 로켓펀치 회사 정보에도 나와있음.(아주 아주 좋은 곳에서 투자를 받았다고 자부함_자본주의만세) - 모두 영어로 호칭함. 직급 없음. 라떼는 말이야 식의 꼰대짓 없음. - 토익 토플 점수 보지 않음(대표는 토익을 본적도 없다함) - 대학교 학점 보지 않음. 졸업장 없어도 상관없음.- 음식 지식에 해박해서 팀 점심 테이블에 소스 아이템 추가의 은혜를 내려주실 분(현재 사무실에는 스리라차 소스와 트러플 오일까지 구비되어있음)- 휴가는 그날 아침에 Feel 꽂혀도 쓸 수 있어야 진정한 휴가임(우리는 그러함. Slack으로 일방통보)- 점심은 회사에서 냄(요기요 VVIP임) - 회식 없음(창립이래 해본적이 한번도 없음). 항상 점심을 다같이 먹고 있음. \u003c 팀 소개 \u003ehttps://www.notion.so/crunchprice/29-767aa3d121834717a28c9cdd17b59633\u003c 아 맞다 업무적으로는, \u003e - iMac, Macbook을 잘 다뤄줄 수 있는 분(다뤄본적이 없으시면 이번에 한번 배워보실 분)- 쿠팡의 로켓배송을 사용해본적이 있고, 배달의 민족에서 치킨 시켜본적이 있는 분- 쇼핑에 관심은 없었으나 이제 쇼핑의 신으로 거듭나고자 하는 분- 참고로 우리는 팀원의 반이 개발직군임. CTO와 Back-end, Front-end 다 있어서 외롭지 않을거임.- 본인의 실력이 경험과 경력에 비해서 훨씬 뛰어나지만, 꿈을 펼쳐보지 못하셨던 분(우리는 경력, 경험보다 실력이 중요함) - 뛰어난 구글링을 자랑하는 분(이미 답은 인터넷에 있으니까 빨리 찾는 것이 내 실력임)\n\n      ","\n        업무 관련 기술 / 활동 분야\n        \n          Android\n          Java\n          PHP\n          Python\n          iOS\n          MySQL\n          Amazon AWS\n          React\n          react-native\n        \n      ","\n        채용 상세\n                    \u003c 담당업무 \u003e - Web은 React, app은 React Native로 개발할 수 있는 사람.  - 본인이 이 서비스를 사용할때 불편함을 본인이 직접 풀어줄수 있는 고객님이자 개발자느님. \u003c 회사위치 및 근무 환경 \u003e- 강남역, 역삼역, 양재역에서 내리면 버스 1회 혹은 킥보드 1회로 올수 있는 거리임. - 항상 간식들이 있…\n            더 보기\n            \u003c 담당업무 \u003e - Web은 React, app은 React Native로 개발할 수 있는 사람.  - 본인이 이 서비스를 사용할때 불편함을 본인이 직접 풀어줄수 있는 고객님이자 개발자느님. \u003c 회사위치 및 근무 환경 \u003e- 강남역, 역삼역, 양재역에서 내리면 버스 1회 혹은 킥보드 1회로 올수 있는 거리임. - 항상 간식들이 있고(대표가 건강에 미쳐있어서 에너지바가 항상 있음), 요즘은 커피 머신 렌탈을 알아보고 있음. - 회식은 없는데, 팀원끼리 안친한게 아니라 일끝나면 퇴근하고 집에가는 삶이 좋지 않은가 싶음(대표가 있든 없든 그냥 본인 일 끝나면 집에 다들감) - 연봉은 내규(이전 연봉보다는 최소 100만원이상 올려줌)\n\n            \n              \n                  \n                \n            \n          \n            \n              \n                  \n                  \n                \n            \n          "]}