{"url":"https://www.rocketpunch.com//jobs/67095/%ED%82%A4%EC%98%A4%EC%8A%A4%ED%81%AC%EC%9B%B9-%EA%B8%B0%EB%B0%98-%ED%94%84%EB%A1%A0%ED%8A%B8%EC%95%A4%EB%93%9C-%EA%B0%9C%EB%B0%9C","title":"키오스크(웹 기반) 프론트앤드 개발","origin":"플랜즈커피","start_date":"12/19 ","newbie":"신입","content":["\n        주요 업무\n                    현재 운영중인 무인 카페 베타의 키오스크 추가 개발 및 UI/UX 고도화 작업에 참여하시고 운영하는 업무입니다.개발 팀으로 구성되어 함께 개발하는 문화이기 때문에, 협업능력이 중요하며 이를 통한 시너지를 기대하고 있습니다.가장 수준 높은 비대면 구매환경을 구현하고자 합니다. Electron.js 기반 React.js 이용한 프론트앤드 개발능력이 요구…\n            더 보기\n            현재 운영중인 무인 카페 베타의 키오스크 추가 개발 및 UI/UX 고도화 작업에 참여하시고 운영하는 업무입니다.개발 팀으로 구성되어 함께 개발하는 문화이기 때문에, 협업능력이 중요하며 이를 통한 시너지를 기대하고 있습니다.가장 수준 높은 비대면 구매환경을 구현하고자 합니다. Electron.js 기반 React.js 이용한 프론트앤드 개발능력이 요구되며,키오스크 개발이지만, 웹 개발 커리어와 비슷한 능력이 요구됩니다.같이 학습하고 실제로 이를 적용하며, 자신이 만든 구현물을 가장 앞 단의 소비자들에게 선보이고 싶은 욕구가 있으신 분이라면 누구나 환영합니다.\n\n      ","\n        업무 관련 기술 / 활동 분야\n        \n          JavaScript\n          React.js\n          Firebase\n          Electron.js\n        \n      ","\n        채용 상세\n                    담당업무- 키오스크(웹 개발: electron.js, react.js) 개발 및 운영- 임베디드 시스템(PCB, Payment, QR reader, ...) serial 통신 모듈 개발- UI/UX 고도화 작업 참여자격요건- 컴퓨터공학 전공자 및 현업 경험- javascript, css, html 를 이용한 개발 경험 또는 이해가 중간 이상- Lin…\n            더 보기\n            담당업무- 키오스크(웹 개발: electron.js, react.js) 개발 및 운영- 임베디드 시스템(PCB, Payment, QR reader, ...) serial 통신 모듈 개발- UI/UX 고도화 작업 참여자격요건- 컴퓨터공학 전공자 및 현업 경험- javascript, css, html 를 이용한 개발 경험 또는 이해가 중간 이상- Linux 운영체제에 대한 기본적인 이해- 웹브라우저에 대한 기본적인 이해- Git에 대한 기본적인 이해우대사항- Firebase- Electron.js- React.js- TDD(Jest)- Webpack- Travis CI\n\n            \n              \n                  \n                \n            \n          \n            \n              \n                  \n                  \n                \n            \n          "]}