{"url":"https://www.rocketpunch.com//jobs/70014/%EB%A7%88%EC%BC%80%ED%8C%85-%EB%B0%8F-%ED%99%8D%EB%B3%B4-%EB%8B%B4%EB%8B%B9%EC%9E%90-%EB%AA%A8%EC%A7%91","title":"마케팅 및 홍보 담당자 모집","origin":"에너닷","start_date":"","newbie":false,"content":["\n        주요 업무\n                    에너닷은 분산전원의 확대로 빠르게 변화하는 에너지산업에서 데이터를 통해 신재생에너지원을 통합 운영, 관리, 및 활용할 수 있는 에너지 데이터 플랫폼을 제공하고 있습니다. 신재생에너지 데이터와 4차산업 기술을 결합한 에너닷만의 기술로 시장 참여자들 간 정보교류를 활성화하고 다양한 편익을 제공할 있는 서비스들을 단계적으로 에너지 시장에 도입하고 있습니다…\n            더 보기\n            에너닷은 분산전원의 확대로 빠르게 변화하는 에너지산업에서 데이터를 통해 신재생에너지원을 통합 운영, 관리, 및 활용할 수 있는 에너지 데이터 플랫폼을 제공하고 있습니다. 신재생에너지 데이터와 4차산업 기술을 결합한 에너닷만의 기술로 시장 참여자들 간 정보교류를 활성화하고 다양한 편익을 제공할 있는 서비스들을 단계적으로 에너지 시장에 도입하고 있습니다. 국내 몇 안되는 에너지 분야  IT기업으로써, 미래 에너지 패러다임의 변화에 대비하여 에너닷만의 독창적인 기술과 비전을 세상에 함께 퍼트릴 열정적인 팀원은 모집합니다.\n\n      ","\n        업무 관련 기술 / 활동 분야\n        \n          온라인마케팅\n          블로그\n          Google Analytics\n          콘텐츠마케팅\n          카피라이팅\n          언론홍보\n          브랜드마케팅\n        \n      ","\n        채용 상세\n                    [담당업무]- 주요 서비스 출시에 따른 user acquisition 캠페인 기획 및 운영 - 인지도 확대를 위한 Contents marketing 전략 수립 및 온라인 마케팅 채널 운영- 그 외 기업 브랜딩 전략 및 신규 마케팅 채널 발굴[자격요건]- 온라인 마케팅 1년 이상의 경력- 학력: 대졸 이상- Data-driven 사고력과 데이터 분석 …\n            더 보기\n            [담당업무]- 주요 서비스 출시에 따른 user acquisition 캠페인 기획 및 운영 - 인지도 확대를 위한 Contents marketing 전략 수립 및 온라인 마케팅 채널 운영- 그 외 기업 브랜딩 전략 및 신규 마케팅 채널 발굴[자격요건]- 온라인 마케팅 1년 이상의 경력- 학력: 대졸 이상- Data-driven 사고력과 데이터 분석 tool (GA) 사용 능력 보유[우대사항]- 스타트업에서의 근무 경험 있는 분- 기타 디자인 tool 활용능력 우대- 새로운 시도에 익숙한 분[근무 조건]- 근무 형태: 정규직 (수습기간 3개월)- 근무요일: 주 5일 - 오전 8시반 ~ 10시 사이 유연적 출근 - 근무지: 서울시 서초구 (교대역 도보 5분 거리)- 급여: 회사 내규에 따름 (면접 후 결정)\n\n            \n              \n                  \n                \n            \n          \n            \n              \n                  \n                \n            \n          \n            \n              \n                  \n+1                \n            \n          \n            \n              \n                  \n                \n            \n          "]}